Metadata-Version: 2.1
Name: potaahto
Version: 0.1.2
Summary: Conversions and redundancy for poor data formatting choices
Home-page: https://gitlab.com/nolash/chainlib
Author: Louis Holbrook
Author-email: dev@holbrook.no
License: WTFPL
Keywords: lint,code,formatting
Classifier: Programming Language :: Python :: 3
Classifier: Operating System :: OS Independent
Classifier: Development Status :: 3 - Alpha
Classifier: Intended Audience :: Developers
Classifier: Topic :: Software Development :: Libraries
Classifier: License :: OSI Approved :: GNU General Public License v3 or later (GPLv3+)
Requires-Python: >=3.6
License-File: LICENSE
